wayfinder/__init__.py
wayfinder/wayfinder.py
wayfinder-1.0.1.dist-info/METADATA
wayfinder-1.0.1.dist-info/WHEEL
wayfinder-1.0.1.dist-info/entry_points.txt
wayfinder-1.0.1.dist-info/license_files/LICENSE
wayfinder-1.0.1.dist-info/RECORD
