Metadata-Version: 2.1
Name: wayfinder
Version: 1.0.1
Summary: A small package containing functions to reliably navigate complex projects
Author-email: Davide Bella <davide.bella89@gmail.com>
License:                     GNU AFFERO GENERAL PUBLIC LICENSE
Classifier: License :: OSI Approved :: MIT License
Classifier: Operating System :: OS Independent
Classifier: Programming Language :: Python :: 3
Requires-Python: >=3.0
